espn_fantasy_server.py
mseep_mcp_espn_ff-0.1.3.dist-info/licenses/LICENSE
mseep_mcp_espn_ff-0.1.3.dist-info/METADATA
mseep_mcp_espn_ff-0.1.3.dist-info/WHEEL
mseep_mcp_espn_ff-0.1.3.dist-info/top_level.txt
mseep_mcp_espn_ff-0.1.3.dist-info/RECORD
